{
    "res" : [{"ship_id" : 0, "path" : [
        {"start_vertex_id" : 13, "end_vertex_id" : 7, "time_start" : 0.0, "time_end" : 5.0},
        {"start_vertex_id" : 7, "end_vertex_id" : 6, "time_start" : 8.0, "time_end" : 10.0}
    ]},
    {"ship_id" : 1, "path" : [
        {"start_vertex_id" : 9, "end_vertex_id" : 24, "time_start" : 1.0, "time_end" : 7.0},
        {"start_vertex_id" : 24, "end_vertex_id" : 12, "time_start" : 13.0, "time_end" : 14.0}
    ]},
    {"ship_id" : 2, "path" : [
        {"start_vertex_id" : 0, "end_vertex_id" : 43, "time_start" : 2.0, "time_end" : 4.0}
    ]}]
}